{
  "caption": "The scene of multiple buildings being damaged after a wildfire",
  "gcg_description": "There are several <p>destroyed buildings</p> [SEG] in the picture.",
  "height": 1024,
  "id": "MjUyNjg1OA.cuJYORmE_yjHYg0PvHgz-lobZhg",
  "img": "santa-rosa-wildfire_00000291_post_disaster.png",
  "phrases": "destroyed building",
  "polygons": [
    [
      [
        [
          367,
          53
        ],
        [
          364,
          75
        ],
        [
          321,
          72
        ],
        [
          321,
          53
        ],
        [
          367,
          53
        ]
      ],
      [
        [
          299,
          301
        ],
        [
          304,
          301
        ],
        [
          306,
          317
        ],
        [
          306,
          326
        ],
        [
          310,
          326
        ],
        [
          317,
          339
        ],
        [
          328,
          342
        ],
        [
          330,
          339
        ],
        [
          351,
          345
        ],
        [
          343,
          374
        ],
        [
          321,
          368
        ],
        [
          324,
          361
        ],
        [
          302,
          356
        ],
        [
          298,
          355
        ],
        [
          289,
          361
        ],
        [
          276,
          344
        ],
        [
          286,
          337
        ],
        [
          284,
          320
        ],
        [
          277,
          321
        ],
        [
          275,
          301
        ],
        [
          299,
          301
        ]
      ],
      [
        [
          508,
          534
        ],
        [
          508,
          552
        ],
        [
          481,
          552
        ],
        [
          481,
          534
        ],
        [
          508,
          534
        ]
      ],
      [
        [
          769,
          544
        ],
        [
          790,
          544
        ],
        [
          789,
          575
        ],
        [
          770,
          575
        ],
        [
          768,
          571
        ],
        [
          743,
          571
        ],
        [
          742,
          553
        ],
        [
          746,
          550
        ],
        [
          766,
          548
        ],
        [
          769,
          544
        ]
      ],
      [
        [
          811,
          682
        ],
        [
          813,
          688
        ],
        [
          786,
          692
        ],
        [
          785,
          685
        ],
        [
          811,
          682
        ]
      ],
      [
        [
          813,
          692
        ],
        [
          816,
          714
        ],
        [
          803,
          718
        ],
        [
          804,
          723
        ],
        [
          795,
          723
        ],
        [
          794,
          719
        ],
        [
          786,
          720
        ],
        [
          782,
          725
        ],
        [
          775,
          724
        ],
        [
          775,
          718
        ],
        [
          767,
          716
        ],
        [
          766,
          705
        ],
        [
          767,
          695
        ],
        [
          813,
          692
        ]
      ],
      [
        [
          785,
          807
        ],
        [
          798,
          807
        ],
        [
          799,
          816
        ],
        [
          801,
          820
        ],
        [
          819,
          820
        ],
        [
          820,
          825
        ],
        [
          825,
          825
        ],
        [
          824,
          839
        ],
        [
          826,
          841
        ],
        [
          826,
          843
        ],
        [
          826,
          844
        ],
        [
          824,
          846
        ],
        [
          823,
          846
        ],
        [
          821,
          846
        ],
        [
          819,
          845
        ],
        [
          819,
          846
        ],
        [
          819,
          849
        ],
        [
          812,
          850
        ],
        [
          803,
          849
        ],
        [
          798,
          850
        ],
        [
          770,
          851
        ],
        [
          770,
          831
        ],
        [
          790,
          830
        ],
        [
          790,
          819
        ],
        [
          785,
          818
        ],
        [
          785,
          807
        ]
      ],
      [
        [
          1023,
          877
        ],
        [
          1013,
          886
        ],
        [
          994,
          865
        ],
        [
          1023,
          842
        ],
        [
          1023,
          877
        ]
      ],
      [
        [
          157,
          885
        ],
        [
          159,
          890
        ],
        [
          163,
          889
        ],
        [
          166,
          900
        ],
        [
          163,
          902
        ],
        [
          166,
          910
        ],
        [
          171,
          908
        ],
        [
          173,
          919
        ],
        [
          168,
          920
        ],
        [
          172,
          934
        ],
        [
          167,
          935
        ],
        [
          164,
          932
        ],
        [
          170,
          962
        ],
        [
          150,
          966
        ],
        [
          139,
          918
        ],
        [
          140,
          915
        ],
        [
          136,
          899
        ],
        [
          138,
          898
        ],
        [
          137,
          890
        ],
        [
          157,
          885
        ]
      ],
      [
        [
          762,
          656
        ],
        [
          772,
          656
        ],
        [
          773,
          664
        ],
        [
          762,
          665
        ],
        [
          761,
          656
        ],
        [
          762,
          656
        ]
      ],
      [
        [
          686,
          564
        ],
        [
          686,
          564
        ],
        [
          697,
          563
        ],
        [
          698,
          571
        ],
        [
          687,
          572
        ],
        [
          685,
          571
        ],
        [
          686,
          564
        ]
      ],
      [
        [
          703,
          560
        ],
        [
          703,
          560
        ],
        [
          712,
          560
        ],
        [
          712,
          572
        ],
        [
          704,
          573
        ],
        [
          703,
          560
        ]
      ],
      [
        [
          679,
          95
        ],
        [
          687,
          91
        ],
        [
          684,
          86
        ],
        [
          692,
          81
        ],
        [
          695,
          86
        ],
        [
          697,
          85
        ],
        [
          702,
          95
        ],
        [
          685,
          105
        ],
        [
          679,
          95
        ]
      ],
      [
        [
          243,
          242
        ],
        [
          280,
          235
        ],
        [
          284,
          258
        ],
        [
          278,
          258
        ],
        [
          279,
          264
        ],
        [
          248,
          269
        ],
        [
          243,
          242
        ]
      ],
      [
        [
          735,
          799
        ],
        [
          748,
          799
        ],
        [
          747,
          811
        ],
        [
          735,
          811
        ],
        [
          735,
          799
        ]
      ],
      [
        [
          481,
          692
        ],
        [
          537,
          627
        ],
        [
          552,
          639
        ],
        [
          537,
          656
        ],
        [
          537,
          668
        ],
        [
          502,
          709
        ],
        [
          481,
          692
        ]
      ],
      [
        [
          715,
          578
        ],
        [
          714,
          557
        ],
        [
          721,
          557
        ],
        [
          722,
          578
        ],
        [
          715,
          578
        ],
        [
          715,
          578
        ]
      ],
      [
        [
          723,
          553
        ],
        [
          742,
          553
        ],
        [
          742,
          579
        ],
        [
          722,
          578
        ],
        [
          723,
          553
        ],
        [
          723,
          553
        ]
      ]
    ]
  ],
  "width": 1024
}