{
  "caption": "The scene of multiple buildings being damaged after a wildfire",
  "gcg_description": "There are several <p>destroyed buildings</p> [SEG] in the picture.",
  "height": 1024,
  "id": "MjU4MDU0OA.HqxVtEAekn4cCFLveFfKUjmBUIA",
  "img": "socal-fire_00000886_post_disaster.png",
  "phrases": "destroyed building",
  "polygons": [
    [
      [
        [
          755,
          81
        ],
        [
          755,
          80
        ],
        [
          778,
          79
        ],
        [
          779,
          91
        ],
        [
          786,
          90
        ],
        [
          788,
          110
        ],
        [
          780,
          111
        ],
        [
          781,
          119
        ],
        [
          763,
          121
        ],
        [
          762,
          115
        ],
        [
          757,
          116
        ],
        [
          755,
          95
        ],
        [
          756,
          95
        ],
        [
          755,
          81
        ]
      ],
      [
        [
          789,
          92
        ],
        [
          791,
          91
        ],
        [
          788,
          80
        ],
        [
          800,
          76
        ],
        [
          816,
          74
        ],
        [
          826,
          109
        ],
        [
          803,
          117
        ],
        [
          804,
          119
        ],
        [
          799,
          121
        ],
        [
          789,
          92
        ]
      ],
      [
        [
          824,
          73
        ],
        [
          838,
          66
        ],
        [
          844,
          79
        ],
        [
          850,
          76
        ],
        [
          860,
          97
        ],
        [
          853,
          100
        ],
        [
          854,
          102
        ],
        [
          836,
          111
        ],
        [
          823,
          86
        ],
        [
          829,
          83
        ],
        [
          824,
          73
        ]
      ],
      [
        [
          856,
          72
        ],
        [
          849,
          59
        ],
        [
          866,
          50
        ],
        [
          887,
          87
        ],
        [
          866,
          99
        ],
        [
          853,
          74
        ],
        [
          856,
          72
        ]
      ],
      [
        [
          884,
          75
        ],
        [
          870,
          35
        ],
        [
          894,
          27
        ],
        [
          896,
          33
        ],
        [
          903,
          30
        ],
        [
          910,
          54
        ],
        [
          903,
          57
        ],
        [
          906,
          66
        ],
        [
          884,
          75
        ]
      ],
      [
        [
          913,
          14
        ],
        [
          913,
          12
        ],
        [
          937,
          9
        ],
        [
          940,
          46
        ],
        [
          935,
          46
        ],
        [
          935,
          51
        ],
        [
          916,
          53
        ],
        [
          916,
          47
        ],
        [
          912,
          48
        ],
        [
          910,
          22
        ],
        [
          913,
          22
        ],
        [
          913,
          14
        ]
      ],
      [
        [
          946,
          35
        ],
        [
          941,
          34
        ],
        [
          944,
          4
        ],
        [
          970,
          8
        ],
        [
          969,
          16
        ],
        [
          974,
          17
        ],
        [
          970,
          44
        ],
        [
          945,
          40
        ],
        [
          946,
          35
        ]
      ],
      [
        [
          1023,
          47
        ],
        [
          1019,
          46
        ],
        [
          1010,
          45
        ],
        [
          1010,
          22
        ],
        [
          1023,
          22
        ],
        [
          1023,
          47
        ]
      ],
      [
        [
          807,
          185
        ],
        [
          776,
          193
        ],
        [
          763,
          149
        ],
        [
          765,
          149
        ],
        [
          797,
          141
        ],
        [
          807,
          185
        ]
      ],
      [
        [
          840,
          175
        ],
        [
          838,
          175
        ],
        [
          840,
          181
        ],
        [
          810,
          189
        ],
        [
          808,
          184
        ],
        [
          808,
          184
        ],
        [
          798,
          141
        ],
        [
          830,
          133
        ],
        [
          840,
          175
        ]
      ],
      [
        [
          868,
          167
        ],
        [
          840,
          175
        ],
        [
          830,
          133
        ],
        [
          858,
          126
        ],
        [
          868,
          167
        ]
      ],
      [
        [
          863,
          125
        ],
        [
          887,
          114
        ],
        [
          900,
          138
        ],
        [
          893,
          143
        ],
        [
          898,
          153
        ],
        [
          879,
          162
        ],
        [
          871,
          147
        ],
        [
          868,
          148
        ],
        [
          864,
          139
        ],
        [
          868,
          137
        ],
        [
          863,
          125
        ]
      ],
      [
        [
          891,
          112
        ],
        [
          910,
          94
        ],
        [
          940,
          131
        ],
        [
          920,
          148
        ],
        [
          915,
          145
        ],
        [
          911,
          149
        ],
        [
          893,
          123
        ],
        [
          897,
          120
        ],
        [
          891,
          112
        ]
      ],
      [
        [
          917,
          91
        ],
        [
          949,
          64
        ],
        [
          966,
          86
        ],
        [
          961,
          90
        ],
        [
          964,
          96
        ],
        [
          941,
          117
        ],
        [
          917,
          91
        ]
      ],
      [
        [
          1023,
          224
        ],
        [
          1011,
          212
        ],
        [
          1023,
          199
        ],
        [
          1023,
          224
        ]
      ],
      [
        [
          1023,
          198
        ],
        [
          1010,
          212
        ],
        [
          986,
          188
        ],
        [
          1016,
          157
        ],
        [
          1023,
          166
        ],
        [
          1023,
          198
        ]
      ],
      [
        [
          1015,
          156
        ],
        [
          986,
          187
        ],
        [
          967,
          169
        ],
        [
          986,
          151
        ],
        [
          982,
          146
        ],
        [
          996,
          133
        ],
        [
          1015,
          156
        ]
      ],
      [
        [
          1023,
          389
        ],
        [
          995,
          383
        ],
        [
          1000,
          362
        ],
        [
          1011,
          364
        ],
        [
          1015,
          345
        ],
        [
          1023,
          346
        ],
        [
          1023,
          389
        ]
      ],
      [
        [
          1023,
          450
        ],
        [
          1011,
          444
        ],
        [
          1023,
          426
        ],
        [
          1023,
          450
        ]
      ],
      [
        [
          970,
          434
        ],
        [
          973,
          429
        ],
        [
          984,
          413
        ],
        [
          989,
          417
        ],
        [
          1002,
          399
        ],
        [
          1018,
          410
        ],
        [
          1013,
          418
        ],
        [
          1019,
          422
        ],
        [
          997,
          452
        ],
        [
          992,
          448
        ],
        [
          990,
          449
        ],
        [
          970,
          434
        ]
      ],
      [
        [
          1023,
          503
        ],
        [
          1012,
          529
        ],
        [
          987,
          520
        ],
        [
          1004,
          481
        ],
        [
          1023,
          488
        ],
        [
          1021,
          493
        ],
        [
          1023,
          494
        ],
        [
          1023,
          503
        ]
      ],
      [
        [
          954,
          507
        ],
        [
          956,
          502
        ],
        [
          968,
          472
        ],
        [
          973,
          474
        ],
        [
          974,
          471
        ],
        [
          998,
          479
        ],
        [
          982,
          518
        ],
        [
          954,
          507
        ]
      ],
      [
        [
          1023,
          669
        ],
        [
          989,
          632
        ],
        [
          1007,
          616
        ],
        [
          1023,
          635
        ],
        [
          1023,
          669
        ]
      ],
      [
        [
          993,
          682
        ],
        [
          965,
          653
        ],
        [
          983,
          635
        ],
        [
          1009,
          661
        ],
        [
          1003,
          667
        ],
        [
          1006,
          669
        ],
        [
          993,
          682
        ]
      ],
      [
        [
          989,
          708
        ],
        [
          1016,
          702
        ],
        [
          1023,
          734
        ],
        [
          1023,
          740
        ],
        [
          996,
          746
        ],
        [
          989,
          708
        ]
      ],
      [
        [
          957,
          761
        ],
        [
          949,
          759
        ],
        [
          953,
          734
        ],
        [
          959,
          734
        ],
        [
          958,
          715
        ],
        [
          965,
          714
        ],
        [
          965,
          712
        ],
        [
          988,
          709
        ],
        [
          992,
          757
        ],
        [
          957,
          761
        ]
      ],
      [
        [
          923,
          756
        ],
        [
          931,
          719
        ],
        [
          955,
          724
        ],
        [
          947,
          763
        ],
        [
          923,
          756
        ]
      ],
      [
        [
          896,
          763
        ],
        [
          904,
          748
        ],
        [
          899,
          745
        ],
        [
          905,
          735
        ],
        [
          910,
          737
        ],
        [
          912,
          732
        ],
        [
          926,
          740
        ],
        [
          917,
          763
        ],
        [
          911,
          761
        ],
        [
          908,
          769
        ],
        [
          896,
          763
        ]
      ],
      [
        [
          829,
          597
        ],
        [
          837,
          592
        ],
        [
          834,
          586
        ],
        [
          857,
          570
        ],
        [
          871,
          592
        ],
        [
          839,
          615
        ],
        [
          829,
          597
        ]
      ],
      [
        [
          853,
          611
        ],
        [
          866,
          612
        ],
        [
          866,
          607
        ],
        [
          880,
          609
        ],
        [
          879,
          616
        ],
        [
          893,
          618
        ],
        [
          891,
          635
        ],
        [
          851,
          631
        ],
        [
          853,
          611
        ]
      ],
      [
        [
          891,
          545
        ],
        [
          919,
          524
        ],
        [
          934,
          542
        ],
        [
          907,
          565
        ],
        [
          891,
          545
        ]
      ],
      [
        [
          1023,
          584
        ],
        [
          1020,
          590
        ],
        [
          1010,
          595
        ],
        [
          1008,
          590
        ],
        [
          997,
          585
        ],
        [
          995,
          589
        ],
        [
          986,
          586
        ],
        [
          995,
          560
        ],
        [
          1001,
          552
        ],
        [
          1002,
          551
        ],
        [
          1023,
          563
        ],
        [
          1023,
          584
        ]
      ],
      [
        [
          994,
          561
        ],
        [
          984,
          587
        ],
        [
          983,
          593
        ],
        [
          956,
          580
        ],
        [
          969,
          549
        ],
        [
          994,
          561
        ]
      ],
      [
        [
          914,
          600
        ],
        [
          920,
          589
        ],
        [
          925,
          591
        ],
        [
          932,
          582
        ],
        [
          960,
          597
        ],
        [
          951,
          619
        ],
        [
          914,
          600
        ]
      ],
      [
        [
          925,
          572
        ],
        [
          931,
          548
        ],
        [
          937,
          549
        ],
        [
          938,
          539
        ],
        [
          960,
          545
        ],
        [
          954,
          571
        ],
        [
          950,
          586
        ],
        [
          925,
          572
        ]
      ],
      [
        [
          937,
          940
        ],
        [
          952,
          934
        ],
        [
          964,
          961
        ],
        [
          948,
          968
        ],
        [
          937,
          940
        ]
      ],
      [
        [
          917,
          914
        ],
        [
          925,
          910
        ],
        [
          934,
          906
        ],
        [
          944,
          928
        ],
        [
          933,
          931
        ],
        [
          928,
          937
        ],
        [
          917,
          914
        ]
      ],
      [
        [
          928,
          937
        ],
        [
          933,
          931
        ],
        [
          944,
          928
        ],
        [
          944,
          932
        ],
        [
          928,
          937
        ]
      ],
      [
        [
          936,
          901
        ],
        [
          945,
          897
        ],
        [
          950,
          910
        ],
        [
          941,
          913
        ],
        [
          936,
          901
        ]
      ],
      [
        [
          992,
          898
        ],
        [
          989,
          899
        ],
        [
          974,
          907
        ],
        [
          972,
          904
        ],
        [
          991,
          895
        ],
        [
          992,
          898
        ]
      ],
      [
        [
          1016,
          892
        ],
        [
          1004,
          897
        ],
        [
          1004,
          896
        ],
        [
          993,
          900
        ],
        [
          993,
          899
        ],
        [
          993,
          899
        ],
        [
          991,
          895
        ],
        [
          972,
          904
        ],
        [
          967,
          890
        ],
        [
          980,
          884
        ],
        [
          981,
          888
        ],
        [
          989,
          884
        ],
        [
          990,
          886
        ],
        [
          998,
          881
        ],
        [
          994,
          874
        ],
        [
          1006,
          868
        ],
        [
          1016,
          892
        ]
      ],
      [
        [
          1018,
          897
        ],
        [
          1006,
          903
        ],
        [
          1004,
          897
        ],
        [
          1016,
          892
        ],
        [
          1018,
          897
        ]
      ],
      [
        [
          984,
          830
        ],
        [
          1002,
          824
        ],
        [
          1008,
          841
        ],
        [
          990,
          847
        ],
        [
          984,
          830
        ]
      ],
      [
        [
          963,
          840
        ],
        [
          969,
          837
        ],
        [
          968,
          834
        ],
        [
          974,
          831
        ],
        [
          979,
          847
        ],
        [
          967,
          850
        ],
        [
          963,
          840
        ]
      ],
      [
        [
          823,
          1023
        ],
        [
          839,
          1009
        ],
        [
          854,
          1023
        ],
        [
          823,
          1023
        ]
      ],
      [
        [
          845,
          232
        ],
        [
          877,
          222
        ],
        [
          879,
          225
        ],
        [
          882,
          234
        ],
        [
          871,
          237
        ],
        [
          871,
          243
        ],
        [
          851,
          249
        ],
        [
          845,
          232
        ]
      ],
      [
        [
          955,
          353
        ],
        [
          941,
          363
        ],
        [
          901,
          313
        ],
        [
          904,
          309
        ],
        [
          898,
          301
        ],
        [
          913,
          287
        ],
        [
          920,
          295
        ],
        [
          926,
          292
        ],
        [
          934,
          301
        ],
        [
          931,
          305
        ],
        [
          962,
          345
        ],
        [
          955,
          353
        ]
      ],
      [
        [
          881,
          241
        ],
        [
          903,
          264
        ],
        [
          883,
          281
        ],
        [
          891,
          291
        ],
        [
          884,
          298
        ],
        [
          876,
          287
        ],
        [
          857,
          263
        ],
        [
          881,
          241
        ]
      ],
      [
        [
          888,
          239
        ],
        [
          917,
          216
        ],
        [
          919,
          214
        ],
        [
          933,
          204
        ],
        [
          943,
          215
        ],
        [
          944,
          222
        ],
        [
          949,
          225
        ],
        [
          936,
          235
        ],
        [
          929,
          231
        ],
        [
          902,
          255
        ],
        [
          930,
          288
        ],
        [
          920,
          295
        ],
        [
          909,
          280
        ],
        [
          902,
          270
        ],
        [
          903,
          264
        ],
        [
          886,
          244
        ],
        [
          888,
          239
        ]
      ],
      [
        [
          931,
          285
        ],
        [
          959,
          258
        ],
        [
          975,
          273
        ],
        [
          944,
          300
        ],
        [
          931,
          285
        ]
      ],
      [
        [
          916,
          653
        ],
        [
          935,
          679
        ],
        [
          920,
          690
        ],
        [
          902,
          665
        ],
        [
          916,
          653
        ]
      ]
    ]
  ],
  "width": 1024
}