{
  "caption": "The scene of multiple buildings being damaged after a wildfire",
  "gcg_description": "There are several <p>destroyed buildings</p> [SEG] in the picture.",
  "height": 1024,
  "id": "MjU3OTkyMg.dKMS2vQL5EL-lt1-ayghbxeffpo",
  "img": "socal-fire_00000268_post_disaster.png",
  "phrases": "destroyed building",
  "polygons": [
    [
      [
        [
          943,
          824
        ],
        [
          949,
          835
        ],
        [
          920,
          851
        ],
        [
          913,
          838
        ],
        [
          929,
          829
        ],
        [
          931,
          831
        ],
        [
          943,
          824
        ]
      ],
      [
        [
          796,
          891
        ],
        [
          808,
          893
        ],
        [
          807,
          902
        ],
        [
          794,
          900
        ],
        [
          796,
          891
        ]
      ],
      [
        [
          809,
          565
        ],
        [
          812,
          565
        ],
        [
          815,
          571
        ],
        [
          812,
          578
        ],
        [
          803,
          577
        ],
        [
          801,
          569
        ],
        [
          809,
          565
        ]
      ],
      [
        [
          992,
          487
        ],
        [
          997,
          491
        ],
        [
          991,
          497
        ],
        [
          987,
          491
        ],
        [
          992,
          487
        ]
      ],
      [
        [
          987,
          215
        ],
        [
          993,
          225
        ],
        [
          986,
          229
        ],
        [
          981,
          218
        ],
        [
          987,
          215
        ]
      ],
      [
        [
          994,
          236
        ],
        [
          1007,
          256
        ],
        [
          986,
          269
        ],
        [
          973,
          248
        ],
        [
          994,
          236
        ]
      ],
      [
        [
          996,
          284
        ],
        [
          997,
          284
        ],
        [
          1000,
          284
        ],
        [
          1002,
          285
        ],
        [
          1003,
          287
        ],
        [
          1002,
          292
        ],
        [
          999,
          293
        ],
        [
          996,
          292
        ],
        [
          994,
          288
        ],
        [
          996,
          284
        ]
      ],
      [
        [
          1009,
          299
        ],
        [
          1011,
          304
        ],
        [
          1006,
          308
        ],
        [
          1003,
          303
        ],
        [
          1009,
          299
        ]
      ],
      [
        [
          104,
          692
        ],
        [
          114,
          696
        ],
        [
          109,
          708
        ],
        [
          99,
          704
        ],
        [
          104,
          692
        ]
      ],
      [
        [
          38,
          440
        ],
        [
          40,
          440
        ],
        [
          42,
          441
        ],
        [
          44,
          444
        ],
        [
          43,
          448
        ],
        [
          37,
          451
        ],
        [
          33,
          448
        ],
        [
          33,
          442
        ],
        [
          38,
          440
        ]
      ],
      [
        [
          30,
          449
        ],
        [
          38,
          463
        ],
        [
          20,
          474
        ],
        [
          10,
          457
        ],
        [
          17,
          452
        ],
        [
          19,
          455
        ],
        [
          30,
          449
        ]
      ],
      [
        [
          33,
          290
        ],
        [
          35,
          301
        ],
        [
          21,
          305
        ],
        [
          19,
          295
        ],
        [
          33,
          290
        ]
      ],
      [
        [
          227,
          332
        ],
        [
          238,
          349
        ],
        [
          230,
          354
        ],
        [
          234,
          363
        ],
        [
          215,
          372
        ],
        [
          218,
          379
        ],
        [
          163,
          406
        ],
        [
          149,
          374
        ],
        [
          171,
          363
        ],
        [
          174,
          369
        ],
        [
          183,
          364
        ],
        [
          179,
          357
        ],
        [
          227,
          332
        ]
      ],
      [
        [
          324,
          181
        ],
        [
          330,
          178
        ],
        [
          336,
          189
        ],
        [
          329,
          192
        ],
        [
          324,
          181
        ]
      ],
      [
        [
          255,
          231
        ],
        [
          276,
          246
        ],
        [
          265,
          265
        ],
        [
          244,
          251
        ],
        [
          255,
          231
        ]
      ],
      [
        [
          195,
          224
        ],
        [
          206,
          231
        ],
        [
          191,
          252
        ],
        [
          180,
          244
        ],
        [
          195,
          224
        ]
      ],
      [
        [
          228,
          256
        ],
        [
          234,
          258
        ],
        [
          230,
          265
        ],
        [
          224,
          263
        ],
        [
          228,
          256
        ]
      ],
      [
        [
          171,
          255
        ],
        [
          175,
          268
        ],
        [
          122,
          283
        ],
        [
          119,
          269
        ],
        [
          171,
          255
        ]
      ],
      [
        [
          135,
          171
        ],
        [
          139,
          177
        ],
        [
          130,
          183
        ],
        [
          127,
          177
        ],
        [
          135,
          171
        ]
      ],
      [
        [
          97,
          127
        ],
        [
          107,
          124
        ],
        [
          110,
          140
        ],
        [
          100,
          142
        ],
        [
          97,
          127
        ]
      ],
      [
        [
          65,
          87
        ],
        [
          82,
          90
        ],
        [
          81,
          99
        ],
        [
          64,
          97
        ],
        [
          65,
          87
        ]
      ],
      [
        [
          103,
          97
        ],
        [
          119,
          95
        ],
        [
          120,
          103
        ],
        [
          104,
          105
        ],
        [
          103,
          97
        ]
      ]
    ]
  ],
  "width": 1024
}